pymidantic/__init__.py
pymidantic/migratable.py
pymidantic-0.1.0.dist-info/METADATA
pymidantic-0.1.0.dist-info/WHEEL
pymidantic-0.1.0.dist-info/RECORD
