Metadata-Version: 2.1
Name: pymidantic
Version: 0.1.0
Summary: 
Author: wheelsandmetal
Requires-Python: >=3.11,<4.0
Classifier: Programming Language :: Python :: 3
Classifier: Programming Language :: Python :: 3.11
Classifier: Programming Language :: Python :: 3.12
Requires-Dist: pydantic (>=2.8.2,<3.0.0)
